pastas/__init__.py
pastas/check.py
pastas/dataset.py
pastas/decorators.py
pastas/forecast.py
pastas/model.py
pastas/modelstats.py
pastas/noisemodels.py
pastas/objective_functions.py
pastas/rcparams.py
pastas/recharge.py
pastas/rfunc.py
pastas/solver.py
pastas/stressmodels.py
pastas/timer.py
pastas/timeseries.py
pastas/timeseries_utils.py
pastas/transform.py
pastas/utils.py
pastas/version.py
pastas/extensions/__init__.py
pastas/extensions/accessor.py
pastas/io/__init__.py
pastas/io/base.py
pastas/io/pas.py
pastas/plotting/__init__.py
pastas/plotting/bokeh.py
pastas/plotting/modelcompare.py
pastas/plotting/modelplots.py
pastas/plotting/plotly.py
pastas/plotting/plots.py
pastas/plotting/plotutil.py
pastas/stats/__init__.py
pastas/stats/core.py
pastas/stats/dutch.py
pastas/stats/metrics.py
pastas/stats/sgi.py
pastas/stats/signatures.py
pastas/stats/tests.py
pastas/typing/__init__.py
pastas/typing/types.py
pastas-1.12.0.dist-info/licenses/LICENSE
pastas-1.12.0.dist-info/METADATA
pastas-1.12.0.dist-info/WHEEL
pastas-1.12.0.dist-info/top_level.txt
pastas-1.12.0.dist-info/RECORD
