Metadata-Version: 2.4
Name: pastas
Version: 1.12.0
Summary: Pastas is an open-source Python framework for the analysis of groundwater time series.
Author: Collenteur et al. 2019
Maintainer-email: "R.A. Collenteur" <raoulcollenteur@gmail.com>, "M. Bakker" <markbak@gmail.com>, "R. Calje" <r.calje@artesia-water.nl>, "F. Schaars" <f.schaars@artesia-water.nl>, "D.A. Brakenhoff" <d.brakenhoff@artesia-water.nl>, "O.N. Ebbens" <o.ebbens@artesia-water.nl>, "M.A. Vonk" <vonk.mart@gmail.com>
License: The MIT License (MIT)
Project-URL: homepage, https://pastas.dev
Project-URL: repository, https://github.com/pastas/pastas
Project-URL: documentation, https://pastas.readthedocs.io
Project-URL: download, https://pypi.org/project/pastas/
Keywords: hydrology,groundwater,timeseries,analysis
Classifier: Development Status :: 5 - Production/Stable
Classifier: Intended Audience :: Science/Research
Classifier: Intended Audience :: Other Audience
Classifier: License :: OSI Approved :: MIT License
Classifier: Programming Language :: Python :: 3 :: Only
Classifier: Programming Language :: Python :: 3.10
Classifier: Programming Language :: Python :: 3.11
Classifier: Programming Language :: Python :: 3.12
Classifier: Programming Language :: Python :: 3.13
Classifier: Programming Language :: Python :: 3.14
Classifier: Topic :: Scientific/Engineering :: Hydrology
Requires-Python: >=3.10
License-File: LICENSE
Requires-Dist: numpy>=2.0.0
Requires-Dist: matplotlib>=3.9.0
Requires-Dist: pandas>=2.2.2
Requires-Dist: scipy>=1.13.0
Requires-Dist: numba<0.63.0,>=0.60.0; python_version < "3.14"
Requires-Dist: numba>=0.63.0b1; python_version == "3.14"
Provides-Extra: solvers
Requires-Dist: lmfit>=1.3.2; extra == "solvers"
Requires-Dist: emcee>=3.1.5; extra == "solvers"
Provides-Extra: latexify
Requires-Dist: latexify-py; extra == "latexify"
Provides-Extra: interactive
Requires-Dist: bokeh>=3.6; extra == "interactive"
Requires-Dist: plotly; extra == "interactive"
Provides-Extra: datasets
Requires-Dist: requests; extra == "datasets"
Provides-Extra: ruffing
Requires-Dist: ruff; extra == "ruffing"
Provides-Extra: formatting
Requires-Dist: pastas[ruffing]; extra == "formatting"
Provides-Extra: linting
Requires-Dist: pastas[ruffing]; extra == "linting"
Provides-Extra: caching
Requires-Dist: cachetools; extra == "caching"
Provides-Extra: codespelling
Requires-Dist: codespell[toml]; extra == "codespelling"
Provides-Extra: full
Requires-Dist: pastas[caching,datasets,interactive,latexify,solvers]; extra == "full"
Provides-Extra: pytesting
Requires-Dist: pytest>=7; extra == "pytesting"
Requires-Dist: pytest-cov; extra == "pytesting"
Requires-Dist: pytest-sugar; extra == "pytesting"
Provides-Extra: ci
Requires-Dist: pastas[caching,interactive,pytesting,solvers]; extra == "ci"
Requires-Dist: jupyter; extra == "ci"
Requires-Dist: coverage; extra == "ci"
Requires-Dist: corner; extra == "ci"
Requires-Dist: tqdm; extra == "ci"
Provides-Extra: rtd
Requires-Dist: pastas[latexify,solvers]; extra == "rtd"
Requires-Dist: Ipython; extra == "rtd"
Requires-Dist: ipykernel; extra == "rtd"
Requires-Dist: pydata-sphinx-theme; extra == "rtd"
Requires-Dist: sphinx; extra == "rtd"
Requires-Dist: sphinxcontrib-bibtex; extra == "rtd"
Requires-Dist: requests; extra == "rtd"
Requires-Dist: numpydoc; extra == "rtd"
Requires-Dist: sphinx-design; extra == "rtd"
Requires-Dist: myst_nb; extra == "rtd"
Requires-Dist: sphinx-autoapi; extra == "rtd"
Provides-Extra: dev
Requires-Dist: tox; extra == "dev"
Requires-Dist: pre-commit; extra == "dev"
Requires-Dist: pastas[ci,codespelling,rtd,ruffing]; extra == "dev"
Dynamic: license-file
